{
  "properties": [
    {
      "id": "1117",
      "address": "2926 Eliot Circle [4 Units] [om] - 2926 Eliot Circle Units 1 - 4 Westminster, CO 80030",
      "coordinates": {
        "lat": 0,
        "lng": 0
      },
      "maintenance": {
        "lockbox_pickup": "Yes",
        "banner_pickup": "No",
        "exterior_photos": "No",
        "eyes_on_property": "No",
        "earliest_pickup_date": "2025-12-26T07:00:00Z"
      },
      "zapier_record_id": "01KD876R9A7FG12PVQZVWST06D",
      "status": "current",
      "last_updated": "2025-12-24T13:02:37.865Z"
    },
    {
      "id": "1118",
      "address": "2932 Eliot Circle [4 Units] [om] - 2932 Eliot Circle Units 1 - 4 Westminster, CO 80030",
      "coordinates": {
        "lat": 0,
        "lng": 0
      },
      "maintenance": {
        "lockbox_pickup": "Yes",
        "banner_pickup": "No",
        "exterior_photos": "No",
        "eyes_on_property": "No",
        "earliest_pickup_date": "2025-12-25T07:00:00Z"
      },
      "zapier_record_id": "01KD876R64518Q77WA1NEM4A2M",
      "status": "current",
      "last_updated": "2025-12-24T13:02:37.865Z"
    },
    {
      "id": "861",
      "address": "6540 Hwy 2 [10 UNITS] - 6540 Highway 2 Commerce City, CO 80022",
      "coordinates": {
        "lat": 0,
        "lng": 0
      },
      "maintenance": {
        "lockbox_pickup": "Yes",
        "banner_pickup": "No",
        "exterior_photos": "No",
        "eyes_on_property": "No",
        "earliest_pickup_date": "2025-11-05T07:00:00Z"
      },
      "zapier_record_id": "01KD876R2BWR1415KQB372QRRZ",
      "status": "current",
      "last_updated": "2025-12-24T13:02:37.865Z"
    },
    {
      "id": "1115",
      "address": "10352 W 59th Ave Units 1 - 4 Arvada, CO 80004",
      "coordinates": {
        "lat": 0,
        "lng": 0
      },
      "maintenance": {
        "lockbox_pickup": "Yes",
        "banner_pickup": "No",
        "exterior_photos": "No",
        "eyes_on_property": "No",
        "earliest_pickup_date": "2025-11-17T07:00:00Z"
      },
      "zapier_record_id": "01KC6R1RMQE428B0YB4C70R7G8",
      "status": "current",
      "last_updated": "2025-12-24T13:02:37.865Z"
    },
    {
      "id": "1086",
      "address": "13325 Shoshone St Westminster, CO 80234",
      "coordinates": {
        "lat": 0,
        "lng": 0
      },
      "maintenance": {
        "lockbox_pickup": "Yes",
        "banner_pickup": "No",
        "exterior_photos": "No",
        "eyes_on_property": "No",
        "earliest_pickup_date": null
      },
      "zapier_record_id": "01KAHH6HGPEST5BTCH6WWKXB56",
      "status": "current",
      "last_updated": "2025-12-24T13:02:37.865Z"
    },
    {
      "id": "263",
      "address": "4450 Holland St Wheat Ridge, CO 80033",
      "coordinates": {
        "lat": 0,
        "lng": 0
      },
      "maintenance": {
        "lockbox_pickup": "Yes",
        "banner_pickup": "No",
        "exterior_photos": "No",
        "eyes_on_property": "No",
        "earliest_pickup_date": null
      },
      "zapier_record_id": "01KAHH5JH705TXBT02CD7M56GJ",
      "status": "current",
      "last_updated": "2025-12-24T13:02:37.865Z"
    }
  ],
  "last_updated": "2025-12-24T13:02:37.865Z",
  "sync_info": {
    "action": "full_table_sync",
    "trigger_record_id": "01KD876R2BWR1415KQB372QRRZ",
    "total_properties": 6,
    "sync_timestamp": "2025-12-24T13:02:37.865Z"
  }
}